odoo/addons/sale_stock_picking_note/README.rst
odoo/addons/sale_stock_picking_note/__init__.py
odoo/addons/sale_stock_picking_note/__manifest__.py
odoo/addons/sale_stock_picking_note/i18n/ca.po
odoo/addons/sale_stock_picking_note/i18n/de.po
odoo/addons/sale_stock_picking_note/i18n/es.po
odoo/addons/sale_stock_picking_note/i18n/sale_stock_picking_note.pot
odoo/addons/sale_stock_picking_note/models/__init__.py
odoo/addons/sale_stock_picking_note/models/sale_stock.py
odoo/addons/sale_stock_picking_note/readme/CONTRIBUTORS.rst
odoo/addons/sale_stock_picking_note/readme/DESCRIPTION.rst
odoo/addons/sale_stock_picking_note/readme/USAGE.rst
odoo/addons/sale_stock_picking_note/static/description/icon.png
odoo/addons/sale_stock_picking_note/static/description/index.html
odoo/addons/sale_stock_picking_note/tests/__init__.py
odoo/addons/sale_stock_picking_note/tests/test_sale_stock_picking_note.py
odoo/addons/sale_stock_picking_note/views/sale_order_view.xml
odoo/addons/sale_stock_picking_note/views/stock_picking_view.xml
odoo11_addon_sale_stock_picking_note-11.0.1.0.0.99.dev8.dist-info/METADATA
odoo11_addon_sale_stock_picking_note-11.0.1.0.0.99.dev8.dist-info/WHEEL
odoo11_addon_sale_stock_picking_note-11.0.1.0.0.99.dev8.dist-info/top_level.txt
odoo11_addon_sale_stock_picking_note-11.0.1.0.0.99.dev8.dist-info/RECORD
